Metadata-Version: 1.0
Name: nose-show-skipped
Version: 0.1
Summary: A nose plugin to show skipped tests and their messages
Home-page: https://github.com/cpcloud/nose-show-skipped
Author: Phillip Cloud
Author-email: cpcloud@gmail.com
License: BSD 3-clause
Keywords: test unittest nose nosetests plugin
Platform: UNKNOWN
